MANIFEST.in
setup.py
contextminer/__init__.py
contextminer/app.py
contextminer/control.py
contextminer/db.py
contextminer/jinja_filters.py
contextminer/miners.py
contextminer/runner.py
contextminer.egg-info/PKG-INFO
contextminer.egg-info/SOURCES.txt
contextminer.egg-info/dependency_links.txt
contextminer.egg-info/entry_points.txt
contextminer.egg-info/not-zip-safe
contextminer.egg-info/requires.txt
contextminer.egg-info/top_level.txt
contextminer/sources/__init__.py
contextminer/sources/facebook_search.py
contextminer/sources/youtube_insights.py
contextminer/sources/youtube_search.py
contextminer/supervisor/supervisor.conf