Metadata-Version: 1.0
Name: contextminer
Version: 0.1.1
Summary: A framework for collecting and analyzing data from social media sources
Home-page: UNKNOWN
Author: Phillip Quiza
Author-email: pquiza@gmail.com
License: MIT
Platform: UNKNOWN
